nipype_generate_fieldmaps.py
nipype_generate_fieldmaps-0.2.4.dist-info/entry_points.txt
nipype_generate_fieldmaps-0.2.4.dist-info/LICENSE
nipype_generate_fieldmaps-0.2.4.dist-info/WHEEL
nipype_generate_fieldmaps-0.2.4.dist-info/METADATA
nipype_generate_fieldmaps-0.2.4.dist-info/RECORD
