Metadata-Version: 2.1
Name: nipype-generate-fieldmaps
Version: 0.2.4
Summary: Nipype workflow to generate fieldmaps from EPI acquisitions with differing phase-encoding directions
Home-page: https://github.com/andrewrosss/nipype-generate-fieldmaps
Keywords: neuroscience,neuroimaging,nipype,mri,fieldmaps,fsl
Author: Andrew Ross
Author-email: andrew.ross.mail@gmail.com
Requires-Python: >=3.8,<4.0
Classifier: Intended Audience :: Developers
Classifier: Intended Audience :: Healthcare Industry
Classifier: Intended Audience :: Science/Research
Classifier: Operating System :: MacOS
Classifier: Operating System :: Unix
Classifier: Programming Language :: Python
Classifier: Programming Language :: Python :: 3
Classifier: Programming Language :: Python :: 3.10
Classifier: Programming Language :: Python :: 3.8
Classifier: Programming Language :: Python :: 3.9
Classifier: Topic :: Scientific/Engineering
Classifier: Topic :: Scientific/Engineering :: Bio-Informatics
Classifier: Topic :: Scientific/Engineering :: Medical Science Apps.
Classifier: Topic :: Software Development :: Libraries :: Python Modules
Classifier: Topic :: Utilities
Classifier: Typing :: Typed
Requires-Dist: nibabel (>=3.0.0,<4.0.0)
Requires-Dist: nipype (>=1.1.0,<2.0.0)
Project-URL: Documentation, https://github.com/andrewrosss/nipype-generate-fieldmaps
Project-URL: Repository, https://github.com/andrewrosss/nipype-generate-fieldmaps
